gmtorch/__init__.py
gmtorch-0.0.0.dist-info/METADATA
gmtorch-0.0.0.dist-info/WHEEL
gmtorch-0.0.0.dist-info/RECORD
