Metadata-Version: 2.4
Name: gmtorch
Version: 0.0.0
Summary: Probabilistic Generative AI Using Gaussian Mixture
Project-URL: homepage, https://gitlab.kit.edu/ali.darijani/gmtorch
Project-URL: source, https://gitlab.kit.edu/ali.darijani/gmtorch
Project-URL: changelog, https://gitlab.kit.edu/ali.darijani/gmtorch/-/blob/main/CHANGELOG.md
Project-URL: releasenotes, https://gitlab.kit.edu/ali.darijani/gmtorch/-/releases
Project-URL: documentation, https://gitlab.kit.edu/ali.darijani/gmtorch
Project-URL: issues, https://gitlab.kit.edu/ali.darijani/gmtorch/-/issues
Author-email: Ali Darijani <ali.darijani@kit.edu>, Tomass Marks Timmermans <tomass.timmermans@student.kit.edu>
Requires-Python: <4.0,>=3.10
Requires-Dist: torch>=2.9.0
Requires-Dist: torchvision>=0.24.0
